MANIFEST.in
README.md
setup.py
automessage/__init__.py
automessage/main.py
automessage.egg-info/PKG-INFO
automessage.egg-info/SOURCES.txt
automessage.egg-info/dependency_links.txt
automessage.egg-info/top_level.txt